py_apple_signin/__init__.py
py_apple_signin/async_api.py
py_apple_signin/dt.py
py_apple_signin/shared.py
py_apple_signin/sync_api.py
py_apple_signin-0.3.1.dist-info/WHEEL
py_apple_signin-0.3.1.dist-info/METADATA
py_apple_signin-0.3.1.dist-info/RECORD
