Metadata-Version: 2.1
Name: py-apple-signin
Version: 0.3.1
Summary: Apple Sign In Python Server Side impl
Home-page: https://github.com/QiYuTechDev/py_apple_signin
License: MIT
Author: dev
Author-email: dev@qiyutech.tech
Requires-Python: >=3.9,<4.0
Classifier: License :: OSI Approved :: MIT License
Classifier: Programming Language :: Python :: 3
Classifier: Programming Language :: Python :: 3.9
Requires-Dist: aiohttp (>=3.7,<4)
Requires-Dist: cryptography (>=3.0,<4.0)
Requires-Dist: dataclasses-json (>=0.5,<0.6)
Requires-Dist: pyjwt (>=2.0,<3)
Requires-Dist: requests (>=2.24,<3)
Project-URL: Repository, https://github.com/QiYuTechDev/py_apple_signin
